{"cameraMode":{"drawMode":0,"name":"Shaded","section":"Shading Mode"},"sceneLighting":true,"audioPlay":false,"sceneViewState":{"showFog":true,"showMaterialUpdate":false,"showSkybox":true,"showFlares":true,"showImageEffects":true,"showParticleSystems":true},"in2DMode":false,"pivot":{"x":-12.843921661376954,"y":4.160202503204346,"z":6.272713661193848},"rotation":{"x":0.0074578216299414639,"y":0.7038788199424744,"z":-0.007391001097857952,"w":0.710242509841919},"size":13.24134635925293,"orthographic":false}